[
  {
    "text": "Пишите код так, как будто сопровождать его будет склонный к насилию психопат, который знает, где вы живете",
    "author": "Стив Макконнелл"
  },
  {
    "text": "Сложность программы растет до тех пор, пока не превысит способности программиста",
    "author": "Артур Блох. Законы Мэрфи"
  },
  {
    "text": "Ходить по воде и разрабатывать программы, следуя ТЗ, очень просто… если они заморожены",
    "author": "И. Берард"
  },
  {
    "text": "Что разум человека может постигнуть и во что он может поверить, того он способен достичь",
    "author": "Наполеон Хилл"
  },
  {
    "text": "Стремитесь не к успеху, а к ценностям, которые он дает",
    "author": "Альберт Эйнштейн"
  },
  {
    "text": " Своим успехом я обязана тому, что никогда не оправдывалась и не принимала оправданий от других",
    "author": "Флоренс Найтингейл"
  },
  {
    "text": "За свою карьеру я пропустил более 9000 бросков, проиграл почти 300 игр. 26 раз мне доверяли сделать финальный победный бросок, и я промахивался. Я терпел поражения снова, и снова, и снова. И именно поэтому я добился успеха",
    "author": "Майкл Джордан"
  },
  {
    "text": "Сложнее всего начать действовать, все остальное зависит только от упорства",
    "author": "Амелия Эрхарт"
  },
  {
    "text": "Надо любить жизнь больше, чем смысл жизни",
    "author": "Федор Достоевский"
  }
]
